aisearchapi_client/__init__.py
aisearchapi_client/client.py
aisearchapi_client/py.typed
aisearchapi_client/types.py
aisearchapi_client-1.0.8.dist-info/licenses/LICENSE
aisearchapi_client-1.0.8.dist-info/METADATA
aisearchapi_client-1.0.8.dist-info/WHEEL
aisearchapi_client-1.0.8.dist-info/top_level.txt
aisearchapi_client-1.0.8.dist-info/RECORD
