Metadata-Version: 2.4
Name: aisearchapi-client
Version: 1.0.8
Summary: Python client library for AI Search API - search and retrieve intelligent responses with context awareness
Author-email: AI Search API <admin@aisearchapi.io>
Maintainer-email: AI Search API <admin@aisearchapi.io>
License: MIT License
Project-URL: Homepage, https://github.com/aisearchapi/aisearchapi-python
Project-URL: Documentation, https://aisearchapi.readthedocs.io/
Project-URL: Repository, https://github.com/aisearchapi/aisearchapi-python
Project-URL: Issues, https://github.com/aisearchapi/aisearchapi-python/issues
Project-URL: Changelog, https://github.com/aisearchapi/aisearchapi-python/blob/main/CHANGELOG.md
Keywords: langchain,langchain-integration,langchain-extension,langchain-tools,aisearchapi,ai search api,semantic search,web search api,search api,summarization api,summary api,contextual ai,contextual search,ai agents,intelligent agents,llm,large language models,chat models,ai chatbot,nlp,research chain,fact checking,question answering,automation,python ai
Classifier: Development Status :: 4 - Beta
Classifier: Intended Audience :: Developers
Classifier: License :: OSI Approved :: MIT License
Classifier: Operating System :: OS Independent
Classifier: Programming Language :: Python
Classifier: Programming Language :: Python :: 3
Classifier: Programming Language :: Python :: 3.8
Classifier: Programming Language :: Python :: 3.9
Classifier: Programming Language :: Python :: 3.10
Classifier: Programming Language :: Python :: 3.11
Classifier: Programming Language :: Python :: 3.12
Classifier: Topic :: Internet :: WWW/HTTP :: Dynamic Content
Classifier: Topic :: Software Development :: Libraries :: Python Modules
Classifier: Topic :: Scientific/Engineering :: Artificial Intelligence
Classifier: Typing :: Typed
Requires-Python: >=3.8
License-File: LICENSE
Requires-Dist: requests>=2.25.0
Requires-Dist: typing-extensions>=4.0.0; python_version < "3.10"
Provides-Extra: dev
Requires-Dist: pytest>=6.0; extra == "dev"
Requires-Dist: pytest-cov>=2.0; extra == "dev"
Requires-Dist: black>=22.0; extra == "dev"
Requires-Dist: isort>=5.0; extra == "dev"
Requires-Dist: flake8>=4.0; extra == "dev"
Requires-Dist: mypy>=0.900; extra == "dev"
Requires-Dist: types-requests>=2.25.0; extra == "dev"
Provides-Extra: docs
Requires-Dist: sphinx>=4.0; extra == "docs"
Requires-Dist: sphinx-rtd-theme>=1.0; extra == "docs"
Provides-Extra: test
Requires-Dist: pytest>=6.0; extra == "test"
Requires-Dist: pytest-cov>=2.0; extra == "test"
Requires-Dist: pytest-asyncio>=0.18.0; extra == "test"
Requires-Dist: responses>=0.18.0; extra == "test"
Dynamic: license-file
